pyssw/__init__.py
pyssw/ssw.cpython-312-x86_64-linux-gnu.so
pyssw/ssw_wrap.py
pyssw-0.1.7.dist-info/METADATA
pyssw-0.1.7.dist-info/WHEEL
pyssw-0.1.7.dist-info/top_level.txt
pyssw-0.1.7.dist-info/RECORD
