Metadata-Version: 2.1
Name: pyssw
Version: 0.1.7
Summary: Python wrapper for SSW alignment
Home-page: https://github.com/runsheng/pyssw
Author: Runsheng
Author-email: runsheng.lee@gmail.com
License: MIT
